wyn_voice_ultra/__init__.py
wyn_voice_ultra/main.py
wyn_voice_ultra-0.1.0.dist-info/METADATA
wyn_voice_ultra-0.1.0.dist-info/WHEEL
wyn_voice_ultra-0.1.0.dist-info/RECORD
