Metadata-Version: 2.1
Name: wyn-voice-ultra
Version: 0.1.0
Summary: 
Author: eagle0504
Author-email: eagle0504@gmail.com
Requires-Python: >=3.9,<4.0
Classifier: Programming Language :: Python :: 3
Classifier: Programming Language :: Python :: 3.9
Classifier: Programming Language :: Python :: 3.10
Classifier: Programming Language :: Python :: 3.11
Classifier: Programming Language :: Python :: 3.12
Requires-Dist: pyautogen (==0.7.3)
Requires-Dist: pydub (==0.25.1)
Requires-Dist: wyn-voice (==0.1.9)
